{
  "artifact": "oph_family_excitation_evaluator",
  "centering_mode": "trace_zero",
  "diagnostic_required_gap_ratio_d": 0.78,
  "diagnostic_required_gap_ratio_u": 1.3,
  "diagnostic_witness_E_d_log": [
    -1.316955324937525,
    -0.6700893501249496,
    1.9870446750624748
  ],
  "diagnostic_witness_E_u_log": [
    -2.4011226599527764,
    -0.7877546800944474,
    3.1888773400472235
  ],
  "diagnostic_witness_coeffs_d": {
    "linear": 1.652,
    "quadratic": 0.205
  },
  "diagnostic_witness_coeffs_u": {
    "linear": 2.795,
    "quadratic": -0.362
  },
  "family_coordinate_kind": "affine_normalized_ordered_branch_coordinate",
  "family_coordinate_x": [
    -1.0,
    -0.5175863354681689,
    1.0
  ],
  "gap_pair_reduction": {
    "coefficient_recovery": {
      "a_q": "(gamma21_q + gamma32_q)/2",
      "b_q": "((1 + x2)*gamma32_q - (1 - x2)*gamma21_q) / (2*(1 - x2^2))"
    },
    "eigenvalue_recovery": {
      "e1": "-(2*gamma21_q + gamma32_q)/3",
      "e2": "(gamma21_q - gamma32_q)/3",
      "e3": "(gamma21_q + 2*gamma32_q)/3"
    },
    "gamma21_q": "E_q,2 - E_q,1",
    "gamma32_q": "E_q,3 - E_q,2"
  },
  "generated_utc": "2026-03-26T00:30:27Z",
  "input_kind": "ordered_branch_generator_spectral_package",
  "log_insertion_convention": "add_E_q_log_to_both_left_and_right_diagonal_logs",
  "notes": [
    "The smallest reduced live family is not a free three-weight projector ansatz but the exact quadratic family forced by a simple ordered three-point spectrum plus trace-zero centering.",
    "The diagnostic witness coefficients are reference-facing only; they show the rough span the missing evaluator must generate without being promoted to theorem status."
  ],
  "ordered_family_eigenvalues": [
    -0.5186397082680319,
    -0.21627404800912356,
    0.7349137562771554
  ],
  "ordered_spectral_gaps": [
    0.3023656602589083,
    0.9511878042862789
  ],
  "promotion_blocker_cleared": "quark_even_excitation_evaluator_missing",
  "proof_status": "candidate_only",
  "quadratic_family_formula": "E_q_log = ctr(a_q * X_ord + b_q * X_ord^2)",
  "quadratic_polynomial_coeffs_d": {
    "linear": null,
    "quadratic": null
  },
  "quadratic_polynomial_coeffs_u": {
    "linear": null,
    "quadratic": null
  },
  "shared_norm_origin": "charged_dirac_scalarization_restriction",
  "shared_norm_value": 0.9231656602589083,
  "theorem_candidate": "every self-adjoint trace-zero sector-even evaluator diagonal in the ordered projector algebra on a simple three-point spectrum is quadratic in X_ord"
}
